moveread/errors/__init__.py
moveread/errors/annotations.py
moveread/errors/core.py
moveread/errors/db.py
moveread_errors-0.1.3.dist-info/METADATA
moveread_errors-0.1.3.dist-info/WHEEL
moveread_errors-0.1.3.dist-info/top_level.txt
moveread_errors-0.1.3.dist-info/RECORD
