Metadata-Version: 2.1
Name: moveread-errors
Version: 0.1.3
Summary: Error types for the Moveread Core
Author-email: Marcel Claramunt <marcel@moveread.com>
Requires-Python: >=3.10
Requires-Dist: moveread-core
